ALogAnalyze/ALogAnalyze.py
ALogAnalyze/ArrayPlot.py
ALogAnalyze/Config.py
ALogAnalyze/Data3D.py
ALogAnalyze/DataLive.py
ALogAnalyze/DiffFrame.py
ALogAnalyze/Plugin.py
ALogAnalyze/RegexGenerator.py
ALogAnalyze/ShellCMD.py
ALogAnalyze/UI.py
ALogAnalyze/__init__.py
ALogAnalyze/Plugins/0001_PluginExample.py
ALogAnalyze/Plugins/0002_KlogTime2UTC.py
ALogAnalyze/Plugins/0003_Bootprof.py
ALogAnalyze/Plugins/0004_MonotoneCubicSpline.py
ALogAnalyze/Plugins/0005_ListDiffMatch.py
ALogAnalyze/Plugins/0006_MediaPipeHands.py
ALogAnalyze/Plugins/0007_QcomContentsParser.py
ALogAnalyze/Plugins/__init__.py
ALogAnalyze/assets/images/icon.png
ALogAnalyze/template/AndroidSystemWakeup.curf
ALogAnalyze/template/MonotoneCubicSpline.json
ALogAnalyze/template/acc.log
ALogAnalyze/template/bluetooth.txt
ALogAnalyze/template/bootprof_go_20230804.txt
ALogAnalyze/template/bootprof_ref_20230804.txt
ALogAnalyze/template/config.json
ALogAnalyze/template/contents.xml
ALogAnalyze/template/hands.txt
ALogAnalyze/template/kernel_log_6__2021_1118_154505
ALogAnalyze/template/kernel_log_6__2021_1118_154505.UTC.converted
ALogAnalyze/template/usb_connect.txt
ALogAnalyze/template/zcv.txt
ALogAnalyze-0.0.1.dist-info/METADATA
ALogAnalyze-0.0.1.dist-info/WHEEL
ALogAnalyze-0.0.1.dist-info/entry_points.txt
ALogAnalyze-0.0.1.dist-info/top_level.txt
ALogAnalyze-0.0.1.dist-info/RECORD
