Metadata-Version: 2.1
Name: ALogAnalyze
Version: 0.0.1
Summary: Android Log Analyze
Home-page: UNKNOWN
Author: zengjf
Author-email: zengjf42@163.com
License: UNKNOWN
Platform: UNKNOWN
Classifier: Programming Language :: Python :: 3
Classifier: Operating System :: OS Independent
Requires-Python: >=3.0
Requires-Dist: VisualLog >=0.0.15
Requires-Dist: PyQt5
